lib_dzne_sqlite/Where.py
lib_dzne_sqlite/__init__.py
lib_dzne_sqlite/cmd.py
lib_dzne_sqlite/exec.py
lib_dzne_sqlite/fmt.py
lib_dzne_sqlite-0.2.3.dist-info/LICENSE.txt
lib_dzne_sqlite-0.2.3.dist-info/METADATA
lib_dzne_sqlite-0.2.3.dist-info/WHEEL
lib_dzne_sqlite-0.2.3.dist-info/top_level.txt
lib_dzne_sqlite-0.2.3.dist-info/RECORD
