Metadata-Version: 2.1
Name: lib-dzne-sqlite
Version: 0.2.3
Summary: Libary for handling sqlite. 
Author-email: Johannes <johannes-programming@posteo.org>
License: Copyright © 2022 Johannes Horler
Project-URL: Download, https://pypi.org/project/lib-dzne-sqlite/#files
Project-URL: Source, https://github.com/johannes-programming/lib_dzne_sqlite
Classifier: License :: OSI Approved :: MIT License
Classifier: Programming Language :: Python
Classifier: Programming Language :: Python :: 3
Requires-Python: >=3.11
License-File: LICENSE.txt
Requires-Dist: na-quantors >=1.0
